MST_TopOpt/MMA.py
MST_TopOpt/__init__.py
MST_TopOpt/adjoint.py
MST_TopOpt/discretization.py
MST_TopOpt/element_matrices.py
MST_TopOpt/filter_threshold.py
MST_TopOpt/functions.py
MST_TopOpt/heat_discretization.py
MST_TopOpt/logfile.py
MST_TopOpt/material_interpolation.py
MST_TopOpt/optimization.py
MST_TopOpt/optomechanics.py
MST_TopOpt/physics.py
MST_TopOpt/plot.py
MST_TopOpt/solver.py
MST_TopOpt-0.2.2.dist-info/LICENSE
MST_TopOpt-0.2.2.dist-info/METADATA
MST_TopOpt-0.2.2.dist-info/WHEEL
MST_TopOpt-0.2.2.dist-info/top_level.txt
MST_TopOpt-0.2.2.dist-info/RECORD
