Metadata-Version: 2.2
Name: MST_TopOpt
Version: 0.2.2
Summary: A package to solve topology optimization problems that target optica forcesl based on the Maxwell Stress Tensor formalism.
Home-page: https://github.com/bmdaj/MST_TopOpt
Author: <Beñat Martinez de Aguirre Jokisch
Author-email: bmdaj13@gmail.com
Classifier: Programming Language :: Python :: 3
Classifier: License :: OSI Approved :: MIT License
Classifier: Operating System :: OS Independent
Requires-Python: >=3.10
License-File: LICENSE
Requires-Dist: numpy
Requires-Dist: scipy
Requires-Dist: matplotlib
Dynamic: author
Dynamic: author-email
Dynamic: classifier
Dynamic: description
Dynamic: description-content-type
Dynamic: home-page
Dynamic: requires-dist
Dynamic: requires-python
Dynamic: summary
